cdpcurl/__init__.py
cdpcurl/__main__.py
cdpcurl/_version.py
cdpcurl/cdpconfig.py
cdpcurl/cdpcurl.py
cdpcurl/cdpv1sign.py
cdpcurl-1.0.0.dist-info/METADATA
cdpcurl-1.0.0.dist-info/WHEEL
cdpcurl-1.0.0.dist-info/entry_points.txt
cdpcurl-1.0.0.dist-info/licenses/LICENSE
cdpcurl-1.0.0.dist-info/licenses/NOTICE.txt
cdpcurl-1.0.0.dist-info/RECORD
