Metadata-Version: 2.4
Name: cdpcurl
Version: 1.0.0
Summary: A curl-like tool for Cloudera on Cloud (CDP) API requests
Author: Cloudera, Inc.
License:                                  Apache License
License-File: LICENSE
License-File: NOTICE.txt
Keywords: authentication,cdp,cloudera,curl,public_cloud
Classifier: Development Status :: 3 - Alpha
Classifier: Intended Audience :: Developers
Classifier: Intended Audience :: System Administrators
Classifier: License :: OSI Approved :: Apache Software License
Classifier: Natural Language :: English
Classifier: Operating System :: OS Independent
Classifier: Programming Language :: Python
Classifier: Programming Language :: Python :: 3.7
Classifier: Programming Language :: Python :: 3.8
Classifier: Programming Language :: Python :: 3.9
Classifier: Programming Language :: Python :: 3.10
Classifier: Programming Language :: Python :: 3.11
Classifier: Programming Language :: Python :: 3.12
Requires-Python: >=3.7
Requires-Dist: configargparse
Requires-Dist: configparser
Requires-Dist: cryptography>=2.8
Requires-Dist: requests>=2.20.0
Requires-Dist: urllib3>=1.25.3
